tidyms2/__init__.py
tidyms2/operators.py
tidyms2/algorithms/__init__.py
tidyms2/algorithms/raw.py
tidyms2/algorithms/signal.py
tidyms2/annotation/__init__.py
tidyms2/annotation/annotation.py
tidyms2/annotation/annotation_data.py
tidyms2/annotation/config.py
tidyms2/annotation/consensus.py
tidyms2/annotation/correspondence.py
tidyms2/annotation/envelope_finder.py
tidyms2/annotation/mmi_finder.py
tidyms2/annotation/operators.py
tidyms2/assay/__init__.py
tidyms2/assay/assay.py
tidyms2/assay/configuration.py
tidyms2/assay/executors.py
tidyms2/assay/utils.py
tidyms2/chem/__init__.py
tidyms2/chem/atoms.py
tidyms2/chem/config.py
tidyms2/chem/context.py
tidyms2/chem/elements.json
tidyms2/chem/envelope.py
tidyms2/chem/envelope_utils.py
tidyms2/chem/exceptions.py
tidyms2/chem/formula.py
tidyms2/chem/formula_generator.py
tidyms2/chem/isotopes.json
tidyms2/chem/table.py
tidyms2/core/dataflow.py
tidyms2/core/enums.py
tidyms2/core/exceptions.py
tidyms2/core/matrix.py
tidyms2/core/models.py
tidyms2/core/registry.py
tidyms2/core/storage.py
tidyms2/core/operators/__init__.py
tidyms2/core/operators/assay.py
tidyms2/core/operators/base.py
tidyms2/core/operators/matrix.py
tidyms2/core/operators/pipeline.py
tidyms2/core/operators/sample.py
tidyms2/core/utils/__init__.py
tidyms2/core/utils/common.py
tidyms2/core/utils/metrics.py
tidyms2/core/utils/numpy.py
tidyms2/core/utils/transformation.py
tidyms2/io/__init__.py
tidyms2/io/datasets.py
tidyms2/io/matrix.py
tidyms2/io/msdata.py
tidyms2/io/mzml.py
tidyms2/io/reader.py
tidyms2/lcms/__init__.py
tidyms2/lcms/assay.py
tidyms2/lcms/imputer.py
tidyms2/lcms/models.py
tidyms2/lcms/sample_builder.py
tidyms2/lcms/operators/__init__.py
tidyms2/lcms/operators/assay.py
tidyms2/lcms/operators/sample.py
tidyms2/simulation/__init__.py
tidyms2/simulation/base.py
tidyms2/simulation/lcms.py
tidyms2/simulation/utils.py
tidyms2/storage/__init__.py
tidyms2/storage/memory.py
tidyms2/storage/table.py
tidyms2/storage/sqlite/__init__.py
tidyms2-0.2.1.dist-info/METADATA
tidyms2-0.2.1.dist-info/WHEEL
tidyms2-0.2.1.dist-info/RECORD
