Metadata-Version: 2.4
Name: tidyms2
Version: 0.2.1
Summary: Tools to process mass spectrometry data.
Author-email: Gabriel Riquelme <griquelme.chm@gmail.com>
Requires-Python: >=3.11
Requires-Dist: httpx>=0.27.2
Requires-Dist: numpy>=2.1.0
Requires-Dist: pydantic>=2.8.2
Requires-Dist: pyyaml>=6.0.2
Requires-Dist: scikit-learn>=1.5.2
Requires-Dist: scipy>=1.14.1
Requires-Dist: sqlalchemy>=2.0.35
Requires-Dist: uuid-utils>=0.9.0
Provides-Extra: dev
Requires-Dist: commitizen>=3.30.0; extra == 'dev'
Requires-Dist: pre-commit>=4.0.1; extra == 'dev'
Requires-Dist: pyright>=1.1.386; extra == 'dev'
Requires-Dist: pytest-cov>=5.0.0; extra == 'dev'
Requires-Dist: pytest-sugar>=1.0.0; extra == 'dev'
Requires-Dist: pytest>=8.3.3; extra == 'dev'
Requires-Dist: ruff>=0.7.1; extra == 'dev'
Requires-Dist: tach>=0.26.1; extra == 'dev'
Provides-Extra: docs
Requires-Dist: autodoc-pydantic>=2.2.0; extra == 'docs'
Requires-Dist: matplotlib>=3.10.0; extra == 'docs'
Requires-Dist: pydata-sphinx-theme>=0.16.0; extra == 'docs'
Requires-Dist: sphinx-autodoc-typehints>=2.5.0; extra == 'docs'
Requires-Dist: sphinx-copybutton>=0.5.2; extra == 'docs'
Requires-Dist: sphinx-design>=0.6.1; extra == 'docs'
Requires-Dist: sphinx-pyproject>=0.3.0; extra == 'docs'
Requires-Dist: sphinx>=8.1.3; extra == 'docs'
